LICENSE
MANIFEST.in
README.md
requirements.txt
setup.py
docker_registry/__init__.py
docker_registry/drivers/__init__.py
docker_registry/drivers/oss.py
docker_registry_driver_oss.egg-info/PKG-INFO
docker_registry_driver_oss.egg-info/SOURCES.txt
docker_registry_driver_oss.egg-info/dependency_links.txt
docker_registry_driver_oss.egg-info/namespace_packages.txt
docker_registry_driver_oss.egg-info/requires.txt
docker_registry_driver_oss.egg-info/top_level.txt
docker_registry_driver_oss.egg-info/zip-safe