Metadata-Version: 1.1
Name: docker-registry-driver-oss
Version: 0.1.2
Summary: Docker registry ali oss driver
Home-page: https://github.com/chris-jin/docker-registry-driver-oss
Author: Chris Jin
Author-email: chrisjin@outlook.com
License: Apache License
